<annotation>
    <folder>Train</folder>
    <filename>chip2103.jpg</filename>
    <path>C:\Users\604572\Desktop\Sea Lion Counting\results\smaller_bbox_chips\Train\chip2103.jpg</path>
    <source>
        <database>Unknown</database>
    </source>
    <size>
        <width>100</width>
        <height>100</height>
        <depth>3</depth>
    </size>
    <segmented>0</segmented>
    <object>
        <name>adult_females</name>
        <pose>Unspecified</pose>
        <truncated>0</truncated>
        <difficult>0</difficult>
        <bndbox>
            <xmin>45</xmin>
            <ymin>33</ymin>
            <xmax>125</xmax>
            <ymax>113</ymax>
        </bndbox>
    </object>    <object>
        <name>adult_females</name>
        <pose>Unspecified</pose>
        <truncated>0</truncated>
        <difficult>0</difficult>
        <bndbox>
            <xmin>45</xmin>
            <ymin>-1</ymin>
            <xmax>125</xmax>
            <ymax>79</ymax>
        </bndbox>
    </object>    <object>
        <name>adult_females</name>
        <pose>Unspecified</pose>
        <truncated>0</truncated>
        <difficult>0</difficult>
        <bndbox>
            <xmin>38</xmin>
            <ymin>-15</ymin>
            <xmax>118</xmax>
            <ymax>65</ymax>
        </bndbox>
    </object>    <object>
        <name>adult_females</name>
        <pose>Unspecified</pose>
        <truncated>0</truncated>
        <difficult>0</difficult>
        <bndbox>
            <xmin>33</xmin>
            <ymin>33</ymin>
            <xmax>113</xmax>
            <ymax>113</ymax>
        </bndbox>
    </object>    <object>
        <name>adult_females</name>
        <pose>Unspecified</pose>
        <truncated>0</truncated>
        <difficult>0</difficult>
        <bndbox>
            <xmin>22</xmin>
            <ymin>33</ymin>
            <xmax>102</xmax>
            <ymax>113</ymax>
        </bndbox>
    </object>    <object>
        <name>adult_females</name>
        <pose>Unspecified</pose>
        <truncated>0</truncated>
        <difficult>0</difficult>
        <bndbox>
            <xmin>14</xmin>
            <ymin>32</ymin>
            <xmax>94</xmax>
            <ymax>112</ymax>
        </bndbox>
    </object>    <object>
        <name>adult_females</name>
        <pose>Unspecified</pose>
        <truncated>0</truncated>
        <difficult>0</difficult>
        <bndbox>
            <xmin>-4</xmin>
            <ymin>8</ymin>
            <xmax>76</xmax>
            <ymax>88</ymax>
        </bndbox>
    </object>    <object>
        <name>adult_females</name>
        <pose>Unspecified</pose>
        <truncated>0</truncated>
        <difficult>0</difficult>
        <bndbox>
            <xmin>-18</xmin>
            <ymin>-13</ymin>
            <xmax>62</xmax>
            <ymax>67</ymax>
        </bndbox>
    </object>    <object>
        <name>adult_females</name>
        <pose>Unspecified</pose>
        <truncated>0</truncated>
        <difficult>0</difficult>
        <bndbox>
            <xmin>-28</xmin>
            <ymin>16</ymin>
            <xmax>52</xmax>
            <ymax>96</ymax>
        </bndbox>
    </object>    <object>
        <name>juveniles</name>
        <pose>Unspecified</pose>
        <truncated>0</truncated>
        <difficult>0</difficult>
        <bndbox>
            <xmin>17</xmin>
            <ymin>17</ymin>
            <xmax>77</xmax>
            <ymax>77</ymax>
        </bndbox>
    </object>    <object>
        <name>juveniles</name>
        <pose>Unspecified</pose>
        <truncated>0</truncated>
        <difficult>0</difficult>
        <bndbox>
            <xmin>-4</xmin>
            <ymin>-30</ymin>
            <xmax>56</xmax>
            <ymax>30</ymax>
        </bndbox>
    </object>    <object>
        <name>juveniles</name>
        <pose>Unspecified</pose>
        <truncated>0</truncated>
        <difficult>0</difficult>
        <bndbox>
            <xmin>-21</xmin>
            <ymin>8</ymin>
            <xmax>39</xmax>
            <ymax>68</ymax>
        </bndbox>
    </object>
</annotation>
